draw3d_derrick/__init__.py
draw3d_derrick/tools.py
draw3d-0.0.1.dist-info/LICENSE
draw3d-0.0.1.dist-info/METADATA
draw3d-0.0.1.dist-info/WHEEL
draw3d-0.0.1.dist-info/top_level.txt
draw3d-0.0.1.dist-info/RECORD
